{
	"board": {
		"id": "ga4srpmb",
		"name": "v0.2.0",
		"description": "Tasks for gitlo v0.2.0.",
		"tags": [
			"gitlo",
			"kanban",
			"tasks"
		],
		"columnIds": [
			"u6l2oizn",
			"dy49ha5e",
			"cr1ft81t",
			"x7nypu03"
		],
		"archived": false,
		"createdAt": "2025-08-05T15:00:04.465Z",
		"updatedAt": "2025-08-05T15:01:56.045Z"
	},
	"columns": [
		{
			"boardId": "ga4srpmb",
			"id": "u6l2oizn",
			"name": "to do",
			"cardIds": [
				"emy911ft",
				"ecqy2kh9",
				"ysmobz24",
				"o9ibwnwu",
				"8knvdsju"
			],
			"archived": false,
			"createdAt": "2025-08-05T15:00:04.465Z",
			"updatedAt": "2025-08-05T15:01:56.045Z"
		},
		{
			"boardId": "ga4srpmb",
			"id": "dy49ha5e",
			"name": "doing",
			"cardIds": [
				"f609zrjq"
			],
			"archived": false,
			"createdAt": "2025-08-05T15:00:04.465Z",
			"updatedAt": "2025-08-05T15:01:56.045Z"
		},
		{
			"boardId": "ga4srpmb",
			"id": "cr1ft81t",
			"name": "done",
			"cardIds": [],
			"archived": false,
			"createdAt": "2025-08-05T15:00:04.465Z",
			"updatedAt": "2025-08-05T15:00:25.167Z"
		},
		{
			"boardId": "ga4srpmb",
			"id": "x7nypu03",
			"name": "blockers",
			"cardIds": [],
			"archived": false,
			"createdAt": "2025-08-05T15:00:27.548Z",
			"updatedAt": "2025-08-05T15:00:27.548Z"
		}
	],
	"cards": [
		{
			"columnId": "dy49ha5e",
			"id": "f609zrjq",
			"name": "v0.1.1 - scope out tasks for v0.2.0",
			"description": "",
			"archived": false,
			"createdAt": "2025-08-05T15:00:46.222Z",
			"updatedAt": "2025-08-05T15:01:56.045Z"
		},
		{
			"columnId": "u6l2oizn",
			"id": "emy911ft",
			"name": "v0.1.2 - ???",
			"description": "",
			"archived": false,
			"createdAt": "2025-08-05T15:00:50.030Z",
			"updatedAt": "2025-08-05T15:00:50.030Z"
		},
		{
			"columnId": "u6l2oizn",
			"id": "ecqy2kh9",
			"name": "v0.1.3 - ???",
			"description": "",
			"archived": false,
			"createdAt": "2025-08-05T15:00:52.668Z",
			"updatedAt": "2025-08-05T15:00:52.668Z"
		},
		{
			"columnId": "u6l2oizn",
			"id": "ysmobz24",
			"name": "v0.1.4 - ???",
			"description": "",
			"archived": false,
			"createdAt": "2025-08-05T15:00:59.601Z",
			"updatedAt": "2025-08-05T15:00:59.601Z"
		},
		{
			"columnId": "u6l2oizn",
			"id": "8knvdsju",
			"name": "v0.1.5 - ???",
			"description": "",
			"archived": false,
			"createdAt": "2025-08-05T15:01:27.130Z",
			"updatedAt": "2025-08-05T15:01:27.130Z"
		}
	]
}